katana_mcp/README.md
katana_mcp/__init__.py
katana_mcp/__main__.py
katana_mcp/_fastmcp_patches.py
katana_mcp/logging.py
katana_mcp/server.py
katana_mcp/unpack.py
katana_mcp/prompts/__init__.py
katana_mcp/resources/__init__.py
katana_mcp/resources/help.py
katana_mcp/resources/inventory.py
katana_mcp/resources/orders.py
katana_mcp/services/__init__.py
katana_mcp/services/dependencies.py
katana_mcp/templates/README.md
katana_mcp/templates/__init__.py
katana_mcp/templates/error.md
katana_mcp/templates/item_details.md
katana_mcp/templates/item_search_results.md
katana_mcp/templates/order_created.md
katana_mcp/templates/order_fulfilled.md
katana_mcp/templates/order_preview.md
katana_mcp/templates/order_received.md
katana_mcp/templates/order_verification_match.md
katana_mcp/templates/order_verification_no_match.md
katana_mcp/templates/order_verification_partial.md
katana_mcp/templates/stock_summary.md
katana_mcp/tools/__init__.py
katana_mcp/tools/schemas.py
katana_mcp/tools/tool_result_utils.py
katana_mcp/tools/foundation/__init__.py
katana_mcp/tools/foundation/catalog.py
katana_mcp/tools/foundation/inventory.py
katana_mcp/tools/foundation/items.py
katana_mcp/tools/foundation/manufacturing_orders.py
katana_mcp/tools/foundation/orders.py
katana_mcp/tools/foundation/purchase_orders.py
katana_mcp/tools/foundation/sales_orders.py
katana_mcp/tools/workflows/__init__.py
katana_mcp_server-0.29.0.dist-info/METADATA
katana_mcp_server-0.29.0.dist-info/WHEEL
katana_mcp_server-0.29.0.dist-info/entry_points.txt
katana_mcp_server-0.29.0.dist-info/RECORD
