Metadata-Version: 2.4
Name: katana-mcp-server
Version: 0.29.0
Summary: MCP server for Katana Manufacturing ERP
Project-URL: Homepage, https://github.com/dougborg/katana-openapi-client
Project-URL: Repository, https://github.com/dougborg/katana-openapi-client
Project-URL: Documentation, https://dougborg.github.io/katana-openapi-client/
Project-URL: Bug Tracker, https://github.com/dougborg/katana-openapi-client/issues
Author-email: Doug Borg <dougborg@dougborg.org>
Maintainer-email: Doug Borg <dougborg@dougborg.org>
License: MIT
Keywords: ai-tools,claude,erp,katana,manufacturing,mcp,mcp-server,model-context-protocol
Classifier: Development Status :: 3 - Alpha
Classifier: Intended Audience :: Developers
Classifier: License :: OSI Approved :: MIT License
Classifier: Operating System :: OS Independent
Classifier: Programming Language :: Python :: 3
Classifier: Programming Language :: Python :: 3.12
Classifier: Programming Language :: Python :: 3.13
Classifier: Programming Language :: Python :: 3.14
Classifier: Topic :: Office/Business
Classifier: Topic :: Software Development :: Libraries :: Python Modules
Classifier: Typing :: Typed
Requires-Python: >=3.12
Requires-Dist: fastmcp>=2.13.0
Requires-Dist: katana-openapi-client>=0.43.0
Requires-Dist: pydantic>=2.12.0
Requires-Dist: python-dotenv>=1.0.0
Requires-Dist: structlog>=25.5.0
